tissuumaps_schema/__init__.py
tissuumaps_schema/__main__.py
tissuumaps_schema/_cli.py
tissuumaps_schema/base.py
tissuumaps_schema/utils.py
tissuumaps_schema/v00/__init__.py
tissuumaps_schema/v00/base.py
tissuumaps_schema/v00/project.py
tissuumaps_schema/v01/__init__.py
tissuumaps_schema/v01/base.py
tissuumaps_schema/v01/project.py
tissuumaps_schema-1.3.0.dist-info/LICENSE
tissuumaps_schema-1.3.0.dist-info/METADATA
tissuumaps_schema-1.3.0.dist-info/WHEEL
tissuumaps_schema-1.3.0.dist-info/entry_points.txt
tissuumaps_schema-1.3.0.dist-info/top_level.txt
tissuumaps_schema-1.3.0.dist-info/RECORD
