Metadata-Version: 2.1
Name: tissuumaps-schema
Version: 1.3.0
Summary: Pydantic schema for TissUUmaps
Home-page: https://github.com/TissUUmaps/TissUUmaps-schema
Author: SciLifeLab BioImage Informatics Facility (BIIF)
Author-email: biif@scilifelab.se
License: MIT
Classifier: Operating System :: OS Independent
Classifier: Programming Language :: Python :: 3
Classifier: Programming Language :: Python :: 3.9
Classifier: Programming Language :: Python :: 3.10
Classifier: Programming Language :: Python :: 3.11
Classifier: License :: OSI Approved :: MIT License
Requires-Python: >=3.9
License-File: LICENSE
Requires-Dist: click
Requires-Dist: pydantic >=2
